django_subserver/__init__.py
django_subserver/base.py
django_subserver/module_view.py
django_subserver/pattern.py
django_subserver/router.py
django_subserver/urls.py
django_subserver-1.0.3.dist-info/licenses/LICENSE
django_subserver-1.0.3.dist-info/METADATA
django_subserver-1.0.3.dist-info/WHEEL
django_subserver-1.0.3.dist-info/top_level.txt
django_subserver-1.0.3.dist-info/RECORD
