Metadata-Version: 2.4
Name: django_subserver
Version: 1.0.3
Author: Alex Fischer
Author-email: alex@quadrant.net
Classifier: Programming Language :: Python :: 3
Classifier: License :: OSI Approved :: MIT License
Classifier: Operating System :: OS Independent
Requires-Python: >=3.7
License-File: LICENSE
Requires-Dist: Django<6,>=3.0
Dynamic: license-file
